aasr/Requests.py
aasr/__init__.py
aas_r-0.0.5.dist-info/METADATA
aas_r-0.0.5.dist-info/WHEEL
aas_r-0.0.5.dist-info/top_level.txt
aas_r-0.0.5.dist-info/zip-safe
aas_r-0.0.5.dist-info/RECORD
